{
  "project": "拜占庭帝国大战略",
  "version": 2,
  "created_at": "2026-06-21T10:14:08.411726",
  "updated_at": "2026-06-21T10:14:37.597897",
  "terminology": {
    "Byzantine Empire": "拜占庭帝国",
    "Byzantine": "拜占庭",
    "Constantinople": "君士坦丁堡",
    "Justinian": "查士丁尼",
    "Theodora": "狄奥多拉",
    "Belisarius": "贝利撒留",
    "Narses": "纳尔塞斯",
    "Heraclius": "希拉克略",
    "Basileus": "巴西琉斯（皇帝）",
    "Augustus": "奥古斯都",
    "Caesar": "凯撒",
    "Senate": "元老院",
    "Consul": "执政官",
    "Praetorian Guard": "近卫军",
    "Praetorian Prefect": "近卫军长官",
    "Magister Militum": "军事长官",
    "Patriarch": "牧首",
    "Ecumenical Council": "大公会议",
    "Arianism": "阿里乌主义",
    "Monophysitism": "一性论",
    "Orthodoxy": "正教",
    "Council of Nicaea": "尼西亚会议",
    "Edict of Milan": "米兰敕令",
    "Fall of the Western Roman Empire": "西罗马帝国灭亡",
    "Nika Riots": "尼卡暴动",
    "Plague of Justinian": "查士丁尼瘟疫",
    "Legion": "军团",
    "Cataphract": "具装骑兵",
    "Foederati": "同盟者（蛮盟部队）",
    "Limitanei": "边防军",
    "Comitatenses": "野战军",
    "Late Antiquity": "古代晚期",
    "Dark Ages": "黑暗时代",
    "Pax Romana": "罗马和平",
    "Tetrarchy": "四帝共治制",
    "Dominate": "多米纳特制（君主专制）",
    "Principate": "元首制"
  },
  "recent_summaries": [
    {
      "chunk": -1,
      "summary": "非常不同的是，由君士坦丁堡指挥的罗马帝国东部半部的命运。这就是我们现代习惯称之为拜占庭帝国的那个帝国，尽管它的统治者及其臣民始终将其视为罗马帝国，他们几乎无法与古老的希腊城市、曾被君士坦丁在公元330年改造成其帝国首都和新罗马的拜占庭城市产生共鸣。通过征服自己的日耳曼战领主，并在五世纪末导致西罗马帝国灭亡的最高危机中智胜了阿提拉的匈奴人，拜占庭帝国获得了抵抗连续几波入侵者的战略方法，这一方法使它维",
      "time": "2026-06-21T10:14:37.597328"
    }
  ],
  "completed_chapters": [],
  "translated_chunks": [],
  "progress": {
    "current_chunk": 0,
    "total_chunks": 0
  },
  "stats": {
    "total_tokens": 0,
    "chunks_done": 0,
    "total_saves": 0
  }
}